script.py
complyhub-0.0.0.dist-info/METADATA
complyhub-0.0.0.dist-info/WHEEL
complyhub-0.0.0.dist-info/entry_points.txt
complyhub-0.0.0.dist-info/top_level.txt
complyhub-0.0.0.dist-info/RECORD
